funcy-stubs/__init__.pyi
funcy-stubs/_types.py
funcy-stubs/calc.pyi
funcy-stubs/colls.pyi
funcy-stubs/debug.pyi
funcy-stubs/decorators.pyi
funcy-stubs/flow.pyi
funcy-stubs/funcmakers.pyi
funcy-stubs/funcools.pyi
funcy-stubs/funcs.pyi
funcy-stubs/objects.pyi
funcy-stubs/primitives.pyi
funcy-stubs/py.typed
funcy-stubs/seqs.pyi
funcy-stubs/strings.pyi
funcy-stubs/tree.pyi
funcy-stubs/types.pyi
funcy_typing-2.0.8.dist-info/METADATA
funcy_typing-2.0.8.dist-info/WHEEL
funcy_typing-2.0.8.dist-info/licenses/LICENSE
funcy_typing-2.0.8.dist-info/RECORD
