Metadata-Version: 2.4
Name: funcy-typing
Version: 2.0.8
Summary: Stubs for funcy package
Project-URL: Repository, https://github.com/feodor-ra/funcy-stubs
Project-URL: Homepage, https://github.com/feodor-ra/funcy-stubs
Author-email: Ratschew Fedor <feodor.ra@me.com>
License-Expression: MIT
License-File: LICENSE
Keywords: funcy,stubs,types,typing
Classifier: Development Status :: 5 - Production/Stable
Classifier: Intended Audience :: Developers
Classifier: License :: OSI Approved :: MIT License
Classifier: Programming Language :: Python :: 3
Classifier: Programming Language :: Python :: 3.8
Classifier: Programming Language :: Python :: 3.9
Classifier: Programming Language :: Python :: 3.10
Classifier: Programming Language :: Python :: 3.11
Classifier: Programming Language :: Python :: 3.12
Classifier: Programming Language :: Python :: 3.13
Classifier: Topic :: Software Development :: Libraries :: Python Modules
Classifier: Typing :: Stubs Only
Requires-Python: >=3.8
Requires-Dist: funcy~=2.0
Requires-Dist: typing-extensions>=4.11
